stpmex/__init__.py
stpmex/auth.py
stpmex/business_days.py
stpmex/client.py
stpmex/exc.py
stpmex/py.typed
stpmex/types.py
stpmex/utils.py
stpmex/version.py
stpmex/resources/__init__.py
stpmex/resources/base.py
stpmex/resources/cuentas.py
stpmex/resources/ordenes.py
stpmex/resources/saldos.py
tests/__init__.py
tests/config.py
tests/conftest.py
tests/test_auth.py
tests/test_business_days.py
tests/test_client.py
tests/test_utils.py
tests/test_validations.py
stpmex-3.15.1.dist-info/LICENSE
stpmex-3.15.1.dist-info/METADATA
stpmex-3.15.1.dist-info/WHEEL
stpmex-3.15.1.dist-info/top_level.txt
stpmex-3.15.1.dist-info/RECORD
