Metadata-Version: 2.1
Name: stpmex
Version: 3.15.1
Summary: Client library for stpmex.com
Home-page: https://github.com/cuenca-mx/stpmex-python
Author: Cuenca
Author-email: dev@cuenca.com
Classifier: Programming Language :: Python :: 3
Classifier: Programming Language :: Python :: 3.6
Classifier: Programming Language :: Python :: 3.7
Classifier: License :: OSI Approved :: MIT License
Classifier: Operating System :: OS Independent
Requires-Python: >=3.6
License-File: LICENSE
Requires-Dist: cryptography <40.1,>=3.0
Requires-Dist: cuenca-validations <0.12,>=0.4
Requires-Dist: requests >=2.25
Requires-Dist: workalendar <17.0.0,>=16.1.0
